finmlkit/__init__.py
finmlkit/_version.py
finmlkit/bar/__init__.py
finmlkit/bar/base.py
finmlkit/bar/data_model.py
finmlkit/bar/io.py
finmlkit/bar/kit.py
finmlkit/bar/logic.py
finmlkit/bar/utils.py
finmlkit/feature/__init__.py
finmlkit/feature/base.py
finmlkit/feature/kit.py
finmlkit/feature/transforms.py
finmlkit/feature/utils.py
finmlkit/feature/core/__init__.py
finmlkit/feature/core/correlation.py
finmlkit/feature/core/ma.py
finmlkit/feature/core/momentum.py
finmlkit/feature/core/reversion.py
finmlkit/feature/core/time.py
finmlkit/feature/core/trend.py
finmlkit/feature/core/utils.py
finmlkit/feature/core/volatility.py
finmlkit/feature/core/volume.py
finmlkit/feature/core/structural_break/__init__.py
finmlkit/feature/core/structural_break/cusum.py
finmlkit/label/__init__.py
finmlkit/label/kit.py
finmlkit/label/tbm.py
finmlkit/label/trend_scanning.py
finmlkit/label/utils.py
finmlkit/label/weights.py
finmlkit/sampling/__init__.py
finmlkit/sampling/filters.py
finmlkit/utils/__init__.py
finmlkit/utils/log.py
finmlkit-0.1.11.dist-info/licenses/LICENSE
finmlkit-0.1.11.dist-info/METADATA
finmlkit-0.1.11.dist-info/WHEEL
finmlkit-0.1.11.dist-info/top_level.txt
finmlkit-0.1.11.dist-info/RECORD
