Metadata-Version: 2.4
Name: finmlkit
Version: 0.1.11
Summary: Financial ML toolkit
Home-page: https://github.com/quantscious/finmlkit
Author: Dániel Terbe
Author-email: dainel@terbe.dev
License: MIT
Classifier: Programming Language :: Python :: 3
Classifier: License :: OSI Approved :: MIT License
Classifier: Operating System :: OS Independent
Requires-Python: >=3.10
License-File: LICENSE
Requires-Dist: numpy~=2.2.0
Requires-Dist: scipy<2.0,>=1.10.0
Requires-Dist: numba~=0.61.0
Requires-Dist: pandas~=2.2.0
Requires-Dist: python-dotenv~=1.0.1
Requires-Dist: pympler~=1.1
Requires-Dist: tables~=3.10.0
Requires-Dist: tqdm
Provides-Extra: dev
Requires-Dist: pytest>=8.0; extra == "dev"
Requires-Dist: pytest-cov>=6.0; extra == "dev"
Requires-Dist: flake8; extra == "dev"
Requires-Dist: black; extra == "dev"
Dynamic: author
Dynamic: author-email
Dynamic: classifier
Dynamic: description
Dynamic: description-content-type
Dynamic: home-page
Dynamic: license
Dynamic: license-file
Dynamic: provides-extra
Dynamic: requires-dist
Dynamic: requires-python
Dynamic: summary
